thai_citizen_id/__init__.py
thai_citizen_id/extract.py
thai_citizen_id/generate.py
thai_citizen_id/validate.py
thai_citizen_id-0.1.4.dist-info/LICENSE
thai_citizen_id-0.1.4.dist-info/METADATA
thai_citizen_id-0.1.4.dist-info/WHEEL
thai_citizen_id-0.1.4.dist-info/top_level.txt
thai_citizen_id-0.1.4.dist-info/RECORD
