Metadata-Version: 2.1
Name: thai-citizen-id
Version: 0.1.4
Summary: Thailand citizen ID tools
Home-page: https://github.com/nopparuts/thai-citizen-id
Author: Nopparut Saelim
Author-email: ak3.nopparut@gmail.com
Classifier: License :: OSI Approved :: GNU General Public License (GPL)
Classifier: Programming Language :: Python :: 3.9
Classifier: Programming Language :: Python :: 3.10
Classifier: Programming Language :: Python :: 3.11
Requires-Python: >=3.9
License-File: LICENSE
